berbix/__init__.py
berbix-1.0.0.dist-info/LICENSE
berbix-1.0.0.dist-info/METADATA
berbix-1.0.0.dist-info/WHEEL
berbix-1.0.0.dist-info/top_level.txt
berbix-1.0.0.dist-info/RECORD
