Metadata-Version: 2.1
Name: berbix
Version: 1.0.0
Summary: SDK for Berbix integrations
Home-page: https://github.com/berbix/berbix-python
Author: Nick Adams
Author-email: nick@berbix.com
License: UNKNOWN
Platform: UNKNOWN
Classifier: Programming Language :: Python :: 3
Classifier: License :: OSI Approved :: MIT License
Classifier: Operating System :: OS Independent
Requires-Dist: requests
